botfly/__init__.py
botfly/all.py
botfly/autodebug.py
botfly/commands.py
botfly/console.py
botfly/controller.py
botfly/debugger.py
botfly/docopt.py
botfly/exceptions.py
botfly/fsm.py
botfly/parser.py
botfly/ui.py
botfly/__pycache__/__init__.cpython-37.opt-1.pyc
botfly/__pycache__/all.cpython-37.opt-1.pyc
botfly/__pycache__/autodebug.cpython-37.opt-1.pyc
botfly/__pycache__/commands.cpython-37.opt-1.pyc
botfly/__pycache__/console.cpython-37.opt-1.pyc
botfly/__pycache__/controller.cpython-37.opt-1.pyc
botfly/__pycache__/debugger.cpython-37.opt-1.pyc
botfly/__pycache__/docopt.cpython-37.opt-1.pyc
botfly/__pycache__/exceptions.cpython-37.opt-1.pyc
botfly/__pycache__/fsm.cpython-37.opt-1.pyc
botfly/__pycache__/parser.cpython-37.opt-1.pyc
botfly/__pycache__/ui.cpython-37.opt-1.pyc
botfly-0.8.0.data/scripts/botflydb
botfly-0.8.0.dist-info/LICENSE.txt
botfly-0.8.0.dist-info/METADATA
botfly-0.8.0.dist-info/WHEEL
botfly-0.8.0.dist-info/top_level.txt
botfly-0.8.0.dist-info/RECORD
