Metadata-Version: 2.1
Name: botfly
Version: 0.8.0
Summary: Alternative Python debugger using prompt-toolkit.
Home-page: https://github.com/kdart/botfly
Author: Keith Dart
Author-email: keith@dartworks.biz
License: Apache 2.0
Platform: UNKNOWN
Classifier: Development Status :: 5 - Production/Stable
Classifier: Environment :: Console
Classifier: Intended Audience :: Developers
Classifier: License :: OSI Approved :: Apache Software License
Classifier: Programming Language :: Python :: 3 :: Only
Classifier: Topic :: Software Development :: Debuggers
Requires-Dist: prompt-toolkit
